{"commitInfo":{"timestamp":1771588045877,"operation":"MERGE","operationParameters":{"predicate":"[\"((item_name#6120 = item_name#6105) AND (competitor_name#6121 = competitor_name#6110))\"]","matchedPredicates":"[{\"actionType\":\"update\"}]","notMatchedPredicates":"[{\"actionType\":\"insert\"}]","notMatchedBySourcePredicates":"[]"},"readVersion":1,"isolationLevel":"Serializable","isBlindAppend":false,"operationMetrics":{"numTargetRowsCopied":"0","numTargetRowsDeleted":"0","numTargetFilesAdded":"1","numTargetBytesAdded":"1428","numTargetBytesRemoved":"1428","numTargetRowsMatchedUpdated":"2","executionTimeMs":"1588","numTargetRowsInserted":"0","numTargetRowsMatchedDeleted":"0","scanTimeMs":"696","numTargetRowsUpdated":"2","numOutputRows":"2","numTargetRowsNotMatchedBySourceUpdated":"0","numTargetChangeFilesAdded":"0","numSourceRows":"2","numTargetFilesRemoved":"1","numTargetRowsNotMatchedBySourceDeleted":"0","rewriteTimeMs":"361"},"engineInfo":"Apache-Spark/3.5.0 Delta-Lake/3.0.0","txnId":"66486002-1381-4e3f-82a5-daa223744969"}}
{"remove":{"path":"part-00000-4599444f-abe2-4358-af42-993ee5ae4a8d-c000.snappy.parquet","deletionTimestamp":1771588045858,"dataChange":true,"extendedFileMetadata":true,"partitionValues":{},"size":1428,"stats":"{\"numRecords\":2}"}}
{"add":{"path":"part-00000-4d2388fc-e906-4933-969b-0f8bdfbb677d-c000.snappy.parquet","partitionValues":{},"size":1428,"modificationTime":1771588045835,"dataChange":true,"stats":"{\"numRecords\":2,\"minValues\":{\"item_name\":\"BREAD\",\"competitor_name\":\"MARKET_A\",\"competitor_price\":2.211,\"timestamp\":\"2026-02-20 17:16:53.545796\"},\"maxValues\":{\"item_name\":\"MILK\",\"competitor_name\":\"MARKET_B\",\"competitor_price\":3.58,\"timestamp\":\"2026-02-20 17:16:55.546029\"},\"nullCount\":{\"item_name\":0,\"competitor_name\":0,\"competitor_price\":0,\"timestamp\":0}}"}}
